shamirs/__init__.py
shamirs/shamirs.py
shamirs-4.0.0.dist-info/licenses/LICENSE
shamirs-4.0.0.dist-info/METADATA
shamirs-4.0.0.dist-info/WHEEL
shamirs-4.0.0.dist-info/top_level.txt
shamirs-4.0.0.dist-info/RECORD
